fastapi_ws_rpc/__init__.py
fastapi_ws_rpc/_internal/__init__.py
fastapi_ws_rpc/_internal/caller.py
fastapi_ws_rpc/_internal/method_invoker.py
fastapi_ws_rpc/_internal/promise_manager.py
fastapi_ws_rpc/_internal/protocol_handler.py
fastapi_ws_rpc/_internal/protocols.py
fastapi_ws_rpc/_internal/rpc_keepalive.py
fastapi_ws_rpc/_internal/rpc_retry.py
fastapi_ws_rpc/config.py
fastapi_ws_rpc/connection_manager.py
fastapi_ws_rpc/exceptions.py
fastapi_ws_rpc/logger.py
fastapi_ws_rpc/rpc_channel.py
fastapi_ws_rpc/rpc_methods.py
fastapi_ws_rpc/schemas.py
fastapi_ws_rpc/simplewebsocket.py
fastapi_ws_rpc/utils.py
fastapi_ws_rpc/websocket_rpc_client.py
fastapi_ws_rpc/websocket_rpc_endpoint.py
fastapi_ws_rpc-1.1.0.dist-info/LICENSE
fastapi_ws_rpc-1.1.0.dist-info/METADATA
fastapi_ws_rpc-1.1.0.dist-info/WHEEL
fastapi_ws_rpc-1.1.0.dist-info/RECORD
