Metadata-Version: 2.3
Name: fastapi_ws_rpc
Version: 1.1.0
Summary: A fast and durable bidirectional JSON RPC channel over Websockets and FastApi.
License: MIT
Keywords: fastapi,websockets,rpc,json,bidirectional
Author: Or Weis
Author-email: or@permit.io
Requires-Python: >=3.9
Classifier: License :: OSI Approved :: MIT License
Classifier: Operating System :: OS Independent
Classifier: Programming Language :: Python :: 3
Classifier: Programming Language :: Python :: 3.9
Classifier: Programming Language :: Python :: 3.10
Classifier: Programming Language :: Python :: 3.11
Classifier: Programming Language :: Python :: 3.12
Classifier: Programming Language :: Python :: 3.13
Classifier: Topic :: Internet :: WWW/HTTP :: HTTP Servers
Classifier: Topic :: Internet :: WWW/HTTP :: WSGI
Requires-Dist: fastapi (>=0.120.0,<0.121.0)
Requires-Dist: packaging (>=25.0,<26.0)
Requires-Dist: pydantic (>=2.11.3,<3.0.0)
Requires-Dist: tenacity (>=9.1.2,<10.0.0)
Requires-Dist: uvicorn (>=0.38.0,<0.39.0)
Requires-Dist: websockets (>=15.0.1,<16.0.0)
Project-URL: Homepage, https://github.com/permitio/fastapi_websocket_rpc
